{
  "version": "1.0",
  "agents": [
    {
      "id": "414f107b-5507-4758-8e91-94c23074c02c",
      "friendlyName": "hyperspectral-researcher",
      "agentType": "local",
      "workFolder": "/home/kashyap/repos/iprd/gates/hyperspectral/research-hyperspectral",
      "createdAt": "2026-03-16T14:06:24.600Z",
      "os": "linux",
      "icon": "🔵",
      "lastUsed": "2026-03-17T13:53:04.168Z",
      "sessionId": "d74ae659-2ac4-443c-a184-9b5ec0ad237d"
    },
    {
      "id": "c0186540-2e9e-4006-b61b-f8f3fefd7f0c",
      "friendlyName": "mayo-reviewer",
      "agentType": "remote",
      "host": "192.168.1.117",
      "port": 22,
      "username": "Kashyap",
      "authType": "key",
      "keyPath": "/home/kashyap/.ssh/id_ed25519",
      "workFolder": "C:\\Users\\Kashyap\\bkp\\source\\repos\\mcp\\CTBW\\mcp-ctbw",
      "createdAt": "2026-03-16T15:08:54.431Z",
      "os": "windows",
      "icon": "🟢",
      "lastUsed": "2026-03-17T06:06:11.426Z"
    },
    {
      "id": "7f3b968d-96e6-4190-aa6b-6dda1b706307",
      "friendlyName": "apra-edge-vision-reviewer",
      "agentType": "local",
      "workFolder": "/home/kashyap/repos/apra/apra-edge-vision",
      "createdAt": "2026-03-16T16:13:56.969Z",
      "os": "linux",
      "icon": "🟦",
      "lastUsed": "2026-03-17T15:26:42.760Z",
      "sessionId": "36cb5c14-db88-45e9-a377-c75a5d8c21c0"
    },
    {
      "id": "234dfdec-f6cb-46c4-979d-17e67233d7fd",
      "friendlyName": "edge-vision-trainer",
      "agentType": "remote",
      "host": "52.91.9.118",
      "port": 22,
      "username": "ubuntu",
      "authType": "key",
      "keyPath": "/home/kashyap/repos/apra/pems-and-keys/aws-keys",
      "workFolder": "/home/ubuntu/apra-edge-vision",
      "createdAt": "2026-03-16T17:44:06.508Z",
      "os": "linux",
      "icon": "🔴",
      "lastUsed": "2026-03-17T20:13:54.773Z",
      "sessionId": "33997e72-96e7-4d9c-be9d-2d2c23b1917d"
    },
    {
      "id": "72c818e7-383b-45c4-a63e-5e82f6bb5670",
      "friendlyName": "artpec9-camera",
      "agentType": "remote",
      "host": "195.60.68.14",
      "port": 21026,
      "username": "kash",
      "authType": "password",
      "encryptedPassword": "b8f333abbad0ffdda75abb3985fc6e2e:cc4bbf191e965603ccf24de039f02e30:3f2b07c398dc7c",
      "workFolder": "/home/kash",
      "createdAt": "2026-03-17T07:35:22.552Z",
      "os": "linux",
      "icon": "🟡",
      "lastUsed": "2026-03-17T13:41:53.341Z"
    },
    {
      "id": "e9a00bbb-3c05-4cfe-b1ef-cdb8656d5304",
      "friendlyName": "regenmed-dev",
      "agentType": "remote",
      "host": "192.168.1.117",
      "port": 22,
      "username": "Kashyap",
      "authType": "key",
      "keyPath": "/home/kashyap/.ssh/id_ed25519",
      "workFolder": "C:\\Users\\Kashyap\\bkp\\source\\repos\\incytes-app-30",
      "createdAt": "2026-03-17T09:18:51.232Z",
      "os": "windows",
      "icon": "🟣",
      "lastUsed": "2026-03-17T10:34:34.279Z"
    },
    {
      "id": "f2d72e36-10a7-49b1-9943-8bd6b8a63388",
      "friendlyName": "apra-fleet-doer",
      "agentType": "local",
      "workFolder": "/home/kashyap/repos/apra/apra-fleet",
      "createdAt": "2026-03-17T20:31:58.844Z",
      "gitAccess": "push",
      "gitRepos": [
        "Apra-Labs/apra-fleet"
      ],
      "os": "linux",
      "icon": "🟢",
      "lastUsed": "2026-03-18T09:27:42.246Z",
      "sessionId": "3fac264c-df4b-4864-a7de-98d4145724d1"
    },
    {
      "id": "f9541c22-58c3-4cc3-ac9e-d1298a0866ab",
      "friendlyName": "apra-fleet-reviewer",
      "agentType": "remote",
      "host": "192.168.1.117",
      "port": 22,
      "username": "Kashyap",
      "authType": "key",
      "keyPath": "/home/kashyap/.ssh/id_ed25519",
      "workFolder": "C:\\Users\\Kashyap\\bkp\\source\\repos\\apra-fleet",
      "createdAt": "2026-03-17T20:34:44.963Z",
      "gitAccess": "read",
      "gitRepos": [
        "Apra-Labs/apra-fleet"
      ],
      "os": "windows",
      "icon": "🟩",
      "lastUsed": "2026-03-17T20:45:22.413Z",
      "sessionId": "5188e582-c706-4397-9a49-03e48d105077"
    }
  ]
}